{"opciones": [{"nombre": "Clua-Muccio-Fernandez-Abraham", "promedio": {}, "score": 0, "docentes": {"Clua": {"respuestas": 0, "score": 0, "nombre": "Clua"}, "Muccio": {"respuestas": 0, "score": 0, "nombre": "Muccio"}, "Fernandez": {"respuestas": 0, "score": 0, "nombre": "Fernandez"}, "Abraham": {"respuestas": 0, "score": 0, "nombre": "Abraham"}}}, {"nombre": "Mendez-Sim\u00f3 Piqueres", "promedio": {"asistencia": 4.75, "cumple_horarios": 4.5, "buen_trato": 4.92, "clase_organizada": 3.58, "claridad": 3.34, "fomenta_participacion": 4.08, "panorama_amplio": 4.66, "acepta_critica": 4.66, "responde_mails": 4.5}, "score": 0, "docentes": {"Mendez": {"asistencia": 4.5, "cumple_horarios": 4.0, "buen_trato": 4.83, "clase_organizada": 3.17, "claridad": 3.67, "fomenta_participacion": 4.17, "panorama_amplio": 4.33, "acepta_critica": 4.33, "responde_mails": 4.0, "respuestas": 6, "score": 0, "nombre": "Mendez"}, "Sim\u00f3 Piqueres": {"asistencia": 5.0, "cumple_horarios": 5.0, "buen_trato": 5.0, "clase_organizada": 4.0, "claridad": 3.0, "fomenta_participacion": 4.0, "panorama_amplio": 5.0, "acepta_critica": 5.0, "responde_mails": 5.0, "respuestas": 1, "score": 0, "nombre": "Sim\u00f3 Piqueres"}}}, {"nombre": "Mendez-Sim\u00f3 Piqueres", "promedio": {"asistencia": 4.75, "cumple_horarios": 4.5, "buen_trato": 4.92, "clase_organizada": 3.58, "claridad": 3.34, "fomenta_participacion": 4.08, "panorama_amplio": 4.66, "acepta_critica": 4.66, "responde_mails": 4.5}, "score": 0, "docentes": {"Mendez": {"asistencia": 4.5, "cumple_horarios": 4.0, "buen_trato": 4.83, "clase_organizada": 3.17, "claridad": 3.67, "fomenta_participacion": 4.17, "panorama_amplio": 4.33, "acepta_critica": 4.33, "responde_mails": 4.0, "respuestas": 6, "score": 0, "nombre": "Mendez"}, "Sim\u00f3 Piqueres": {"asistencia": 5.0, "cumple_horarios": 5.0, "buen_trato": 5.0, "clase_organizada": 4.0, "claridad": 3.0, "fomenta_participacion": 4.0, "panorama_amplio": 5.0, "acepta_critica": 5.0, "responde_mails": 5.0, "respuestas": 1, "score": 0, "nombre": "Sim\u00f3 Piqueres"}}}]}