[{"Jahn": {"asistencia": 3.6666666666666665, "cumple_horarios": 4.666666666666667, "buen_trato": 2.0, "clase_organizada": 2.3333333333333335, "claridad": 2.3333333333333335, "fomenta_participacion": 2.6666666666666665, "panorama_amplio": 3.0, "acepta_critica": 1.3333333333333333, "responde_mails": 1.6666666666666667}, "Cordova": {"asistencia": 5.0, "cumple_horarios": 5.0, "buen_trato": 4.0, "clase_organizada": 4.0, "claridad": 4.0, "fomenta_participacion": 3.0, "panorama_amplio": 3.0, "acepta_critica": 3.0, "responde_mails": 2.0}, "Mu\u00f1oz": {"asistencia": 5.0, "cumple_horarios": 5.0, "buen_trato": 4.0, "clase_organizada": 3.0, "claridad": 4.0, "fomenta_participacion": 3.0, "panorama_amplio": 3.0, "acepta_critica": 3.0, "responde_mails": 4.0}, "Vallejos": {"asistencia": 4.666666666666667, "cumple_horarios": 4.666666666666667, "buen_trato": 4.333333333333333, "clase_organizada": 3.3333333333333335, "claridad": 3.6666666666666665, "fomenta_participacion": 4.0, "panorama_amplio": 3.0, "acepta_critica": 3.3333333333333335, "responde_mails": 5.0}, "Hachelias": {"asistencia": 3.0, "cumple_horarios": 4.0, "buen_trato": 4.0, "clase_organizada": 4.0, "claridad": 3.0, "fomenta_participacion": 3.0, "panorama_amplio": 3.0, "acepta_critica": 3.0, "responde_mails": 2.0}}]