[{"Argerich": {"asistencia": 4.0, "cumple_horarios": 4.0, "buen_trato": 4.0, "clase_organizada": 3.6666666666666665, "claridad": 4.222222222222222, "fomenta_participacion": 3.888888888888889, "panorama_amplio": 4.444444444444445, "acepta_critica": 3.4444444444444446, "responde_mails": 3.888888888888889}, "Golmar": {"asistencia": 3.375, "cumple_horarios": 3.5, "buen_trato": 4.5, "clase_organizada": 3.5, "claridad": 4.25, "fomenta_participacion": 4.0, "panorama_amplio": 3.75, "acepta_critica": 4.0, "responde_mails": 3.75}, "Martinelli": {"asistencia": 3.5, "cumple_horarios": 3.625, "buen_trato": 3.875, "clase_organizada": 2.75, "claridad": 2.875, "fomenta_participacion": 3.125, "panorama_amplio": 3.125, "acepta_critica": 3.75, "responde_mails": 3.5}, "Ramos Mejia": {"asistencia": 3.4285714285714284, "cumple_horarios": 4.0, "buen_trato": 4.0, "clase_organizada": 2.857142857142857, "claridad": 2.7142857142857144, "fomenta_participacion": 3.0, "panorama_amplio": 3.0, "acepta_critica": 3.7142857142857144, "responde_mails": 3.0}}]