[{"Argerich": {"asistencia": 4.0, "cumple_horarios": 4.0, "buen_trato": 4.0, "clase_organizada": 3.7, "claridad": 4.2, "fomenta_participacion": 3.9, "panorama_amplio": 4.4, "acepta_critica": 3.4, "responde_mails": 3.9}, "Golmar": {"asistencia": 3.4, "cumple_horarios": 3.5, "buen_trato": 4.5, "clase_organizada": 3.5, "claridad": 4.2, "fomenta_participacion": 4.0, "panorama_amplio": 3.8, "acepta_critica": 4.0, "responde_mails": 3.8}, "Martinelli": {"asistencia": 3.5, "cumple_horarios": 3.6, "buen_trato": 3.9, "clase_organizada": 2.8, "claridad": 2.9, "fomenta_participacion": 3.1, "panorama_amplio": 3.1, "acepta_critica": 3.8, "responde_mails": 3.5}, "Ramos Mejia": {"asistencia": 3.4, "cumple_horarios": 4.0, "buen_trato": 4.0, "clase_organizada": 2.9, "claridad": 2.7, "fomenta_participacion": 3.0, "panorama_amplio": 3.0, "acepta_critica": 3.7, "responde_mails": 3.0}}]