[{"Bertuccio": {"asistencia": 4.7, "cumple_horarios": 3.5, "buen_trato": 3.9, "clase_organizada": 2.1, "claridad": 2.3, "fomenta_participacion": 2.9, "panorama_amplio": 2.4, "acepta_critica": 2.7, "responde_mails": 3.9}, "Marchi": {"asistencia": 1.6, "cumple_horarios": 1.8, "buen_trato": 2.8, "clase_organizada": 2.0, "claridad": 2.2, "fomenta_participacion": 1.6, "panorama_amplio": 2.6, "acepta_critica": 2.4, "responde_mails": 2.6}, "Bulacio": {"asistencia": 3.7, "cumple_horarios": 3.6, "buen_trato": 4.1, "clase_organizada": 1.4, "claridad": 3.1, "fomenta_participacion": 1.3, "panorama_amplio": 1.7, "acepta_critica": 3.4, "responde_mails": 3.0}, "Gamez Canocchiella": {}}]